{"code":"U14G","ageGroupCode":"U14","name":"Under 14 Girls","teamGender":"Female","playersTransferred":[{"footyWebNumber":"03070939","status":"Transferred","statusInfo":"Ferntree Gully 2021","initials":"JB","lastName":"Bamford","firstName":"Josephine","dateOfBirth":"2007-06-03","gender":"Female"},{"footyWebNumber":"03399779","status":"Transferred","statusInfo":"Mitcham 2021","initials":"AK","lastName":"King","firstName":"Acacia-Lee","dateOfBirth":"2007-07-08","gender":"Female"}],"playersHistorical":[{"footyWebNumber":"03064435","status":"Historical","statusInfo":"Last registered  unknown","initials":"MG","lastName":"George","firstName":"Maya","dateOfBirth":"2007-08-30","gender":"Female"},{"footyWebNumber":"03251681","status":"Historical","statusInfo":"Last registered 2018","initials":"RH","lastName":"Harrison","firstName":"Rhianna","dateOfBirth":"2008-03-24","gender":"Female"},{"footyWebNumber":"02456464","status":"Historical","statusInfo":"Last registered 2017","initials":"ML","lastName":"Lewis","firstName":"Mikayla","dateOfBirth":"2008-02-23","gender":"Female"},{"footyWebNumber":"02639396","status":"Historical","statusInfo":"Last registered 2018","initials":"AM","lastName":"matheson","firstName":"ava","dateOfBirth":"2007-08-05","gender":"Female"},{"footyWebNumber":"03086852","status":"Historical","statusInfo":"Last registered 2017","initials":"RP","lastName":"Paras","firstName":"Rubee","dateOfBirth":"2008-06-14","gender":"Female"},{"footyWebNumber":"03087991","status":"Historical","statusInfo":"Last registered 2017","initials":"CR","lastName":"Ramadge","firstName":"Chelsea","dateOfBirth":"2007-10-21","gender":"Female"}]}