{"footyWebNumber":"01635651","initials":"JB","lastName":"Bright","firstName":"Jacob","dateOfBirth":"2004-05-11","status":"Transferred","statusInfo":"Wantirna South 2021","club":"Wantirna South","gender":"Male","disability":null,"contacts":[{"type":"Guardian","relationship":"Parent/Guardian","name":"Andrew Bright","gender":"Male","initials":"AB","contactMethods":[{"type":"Phone","value":"03 9729 1911"},{"type":"Phone","value":"0425 817 084"},{"type":"Email","value":"youngandbright@optusnet.com.au"}]},{"type":"Guardian","relationship":"Parent/Guardian","name":"Helen Bright","gender":"Female","initials":"HB","contactMethods":[{"type":"Phone","value":"0438 729 190"},{"type":"Email","value":"youngandbright@optusnet.com.au"},{"type":null,"value":null}]},{"type":"Emergency","relationship":"Emergency Contact (Father)","name":"Andrew Bright","gender":"Unknown","initials":"EC","contactMethods":[{"type":"Phone","value":"0425 817 084"},{"type":null,"value":null},{"type":null,"value":null}]},{"type":"Registered","relationship":"Registered Contact","name":"Registered Contact","gender":"Unknown","initials":"RC","contactMethods":[{"type":"Phone","value":"0425 817 084"},{"type":"Phone","value":"0411 224 520"},{"type":"Email","value":"jacobb04@mail.com"}]}],"transactions":[{"date":"2021-03-24","year":21,"product":"2021 Registration","total":"18.00","status":"Paid"},{"date":"2019-11-21","year":20,"product":"2020 Registration","total":"18.00","status":"Paid"}],"clubHistory":[{"club":"Wantirna South","date":"2021-03-25"}],"team":{"code":"U17B-GOLD","name":"Under 17 Boys (Gold)","ageGroupCode":"U17","teamGender":"Male"}}