{"footyWebNumber":"02282039","initials":"CK","lastName":"kleverkamp","firstName":"cody","dateOfBirth":"2008-06-02","status":"Insured","statusInfo":"Insured","club":"Bayswater","gender":"Male","disability":null,"contacts":[{"type":"Guardian","relationship":"Parent/Guardian","name":"Brendan Kleverkamp","gender":"Male","initials":"BK","contactMethods":[{"type":"Phone","value":"0412 236 531"},{"type":"Phone","value":"0402 126 141"},{"type":"Email","value":"bkck0208@gmail.com"}]},{"type":"Emergency","relationship":"Emergency Contact (Father)","name":"Brendan kleverkamp","gender":"Unknown","initials":"EC","contactMethods":[{"type":"Phone","value":"0412 236 531"},{"type":null,"value":null},{"type":null,"value":null}]},{"type":"Registered","relationship":"Registered Contact","name":"Registered Contact","gender":"Unknown","initials":"RC","contactMethods":[{"type":"Phone","value":"0412 236 531"},{"type":"Phone","value":"0402 126 141"},{"type":"Email","value":"bkck0208@gmail.com"}]}],"transactions":[{"date":"2021-06-19","year":21,"product":"2021 Registration","total":"18.00","status":"Paid"}],"clubHistory":[{"club":"Bayswater","date":"2017-04-01"}],"team":{"code":"U14B","name":"Under 14 Boys","ageGroupCode":"U14","teamGender":"Male"}}