{"footyWebNumber":"03561703","initials":"MC","lastName":"Cincotta","firstName":"Markus","dateOfBirth":"2012-05-19","status":"Recent","statusInfo":"Last registered 2020","club":"Bayswater","gender":"Male","disability":null,"contacts":[{"type":"Guardian","relationship":"Parent/Guardian","name":"Timothy Cincotta","gender":"Male","initials":"TC","contactMethods":[{"type":"Phone","value":"0413 886 251"},{"type":"Email","value":"tscincotta@hotmail.com"},{"type":null,"value":null}]},{"type":"Guardian","relationship":"Parent/Guardian","name":"Chantal Hoppe","gender":"Female","initials":"CH","contactMethods":[{"type":"Phone","value":"0412 124 474"},{"type":"Email","value":"chantal.hoppe@monash.edu.au"},{"type":null,"value":null}]},{"type":"Registered","relationship":"Registered Contact","name":"Registered Contact","gender":"Unknown","initials":"RC","contactMethods":[{"type":"Phone","value":"0413 886 251"},{"type":"Email","value":"tscincotta@hotmail.com"},{"type":null,"value":null}]}],"transactions":[{"date":"2020-02-15","year":20,"product":"2020 Club (U8)","total":"100.00","status":"Paid"},{"date":"2020-02-15","year":20,"product":"2020 Registration","total":"18.00","status":"Paid"}],"clubHistory":[{"club":"Bayswater","date":"2020-02-15"}],"team":{"code":"U09M","name":"Under 9 Mixed","ageGroupCode":"U9","teamGender":"Mixed"}}